synkvaksms/__init__.py
synkvaksms/client.py
synkvaksms/exceptions/__init__.py
synkvaksms/exceptions/bad_request.py
synkvaksms/models/__init__.py
synkvaksms/models/count_number.py
synkvaksms/models/country.py
synkvaksms/models/number.py
synkvaksms/models/services.py
synkvaksms/models/sms.py
synkvaksms-1.0.0.dist-info/METADATA
synkvaksms-1.0.0.dist-info/WHEEL
synkvaksms-1.0.0.dist-info/licenses/LICENSE
synkvaksms-1.0.0.dist-info/RECORD
